{
  "package": "org.openrewrite.unarytest",
  "class": "UnarytestV2",
  "fields": [
    {
      "name": "f1",
      "type": "String",
      "annotations": [
        "@Nullable"
      ],
      "modifiers": [
        "private"
      ]
    },
    {
      "name": "f2",
      "type": "Map<String,String>",
      "annotations": [],
      "modifiers": [
        "private"
      ]
    },
    {
      "name": "f3",
      "type": "String",
      "annotations": [],
      "modifiers": [
        "private"
      ]
    }
  ],
  "methods": [
    {
      "name": "unarytest",
      "params": [],
      "returnType": "BigDecimal",
      "annotations": [],
      "modifiers": [
        "public"
      ],
      "throws": [],
      "summary": "unarytest (synth)"
    },
    {
      "name": "unarytestV1Ext",
      "params": [],
      "returnType": "BigDecimal",
      "annotations": [],
      "modifiers": [
        "protected"
      ],
      "throws": [],
      "summary": "unarytestV1 (synth)"
    },
    {
      "name": "upgrade",
      "params": [
        {
          "name": "p1",
          "type": "long"
        }
      ],
      "returnType": "boolean",
      "annotations": [],
      "modifiers": [
        "public"
      ],
      "throws": [],
      "summary": "upgrade (synth)"
    },
    {
      "name": "orderservice",
      "params": [
        {
          "name": "p1",
          "type": "boolean"
        },
        {
          "name": "p2",
          "type": "BigDecimal"
        }
      ],
      "returnType": "String",
      "annotations": [],
      "modifiers": [
        "public"
      ],
      "throws": [],
      "summary": "orderservice (synth)"
    },
    {
      "name": "orderserviceV1",
      "params": [
        {
          "name": "p1",
          "type": "int"
        }
      ],
      "returnType": "void",
      "annotations": [],
      "modifiers": [
        "public"
      ],
      "throws": [],
      "summary": "orderserviceV1 (synth)"
    },
    {
      "name": "process",
      "params": [
        {
          "name": "p1",
          "type": "int"
        }
      ],
      "returnType": "boolean",
      "annotations": [
        "@Deprecated"
      ],
      "modifiers": [
        "public"
      ],
      "throws": [],
      "summary": "process (synth)"
    }
  ],
  "annotations": [],
  "imports": [
    "java.util.*"
  ]
}