{
  "package": "org.openrewrite.kotlintypegoattest",
  "class": "KotlintypegoattestV2",
  "fields": [],
  "methods": [
    {
      "name": "compute",
      "params": [
        {
          "name": "p1",
          "type": "boolean"
        },
        {
          "name": "p2",
          "type": "boolean"
        }
      ],
      "returnType": "BigDecimal",
      "annotations": [],
      "modifiers": [
        "public"
      ],
      "throws": [],
      "summary": "compute (synth)"
    },
    {
      "name": "transactionservic",
      "params": [
        {
          "name": "p1",
          "type": "int"
        },
        {
          "name": "p2",
          "type": "long"
        }
      ],
      "returnType": "boolean",
      "annotations": [],
      "modifiers": [
        "public"
      ],
      "throws": [],
      "summary": "transactionservic (synth)"
    },
    {
      "name": "upgrade",
      "params": [
        {
          "name": "p1",
          "type": "BigDecimal"
        }
      ],
      "returnType": "String",
      "annotations": [],
      "modifiers": [
        "protected"
      ],
      "throws": [],
      "summary": "upgrade (synth)"
    },
    {
      "name": "upgradeV1",
      "params": [
        {
          "name": "p1",
          "type": "long"
        }
      ],
      "returnType": "String",
      "annotations": [],
      "modifiers": [
        "public"
      ],
      "throws": [],
      "summary": "upgradeV1 (synth)"
    },
    {
      "name": "kotlintypegoattest",
      "params": [],
      "returnType": "String",
      "annotations": [],
      "modifiers": [
        "public"
      ],
      "throws": [],
      "summary": "kotlintypegoattest (synth)"
    },
    {
      "name": "kotlintypegoattestV1",
      "params": [
        {
          "name": "p1",
          "type": "boolean"
        },
        {
          "name": "p2",
          "type": "String"
        }
      ],
      "returnType": "int",
      "annotations": [],
      "modifiers": [
        "public"
      ],
      "throws": [
        "IOException"
      ],
      "summary": "kotlintypegoattestV1 (synth)"
    }
  ],
  "annotations": [],
  "imports": [
    "java.util.*"
  ]
}