{
  "openapi": "3.0.0",
  "info": {
    "title": "synth-openapi-cd1294805fc3",
    "version": "1.0.0"
  },
  "paths": {
    "/synth-openapi-cd1294805fc3/items": {
      "get": {
        "responses": {
          "200": {
            "description": "ok"
          }
        }
      }
    },
    "/synth-openapi-cd1294805fc3/auto31918": {
      "get": {
        "responses": {
          "200": {
            "description": "ok"
          }
        }
      }
    },
    "/synth-openapi-cd1294805fc3/auto25780": {
      "post": {
        "requestBody": {
          "content": {
            "application/json": {
              "schema": {
                "type": "object",
                "properties": {
                  "flag": {
                    "type": "string",
                    "enum": [
                      "a",
                      "b",
                      "c"
                    ]
                  }
                }
              }
            }
          }
        },
        "responses": {
          "201": {
            "description": "created"
          }
        }
      }
    },
    "/synth-openapi-cd1294805fc3/auto85803": {
      "post": {
        "requestBody": {
          "content": {
            "application/json": {
              "schema": {
                "type": "object",
                "properties": {
                  "flag": {
                    "type": "string",
                    "enum": [
                      "a",
                      "b",
                      "c"
                    ]
                  }
                }
              }
            }
          }
        },
        "responses": {
          "201": {
            "description": "created"
          }
        }
      }
    },
    "/synth-openapi-cd1294805fc3/auto46530": {
      "post": {
        "requestBody": {
          "content": {
            "application/json": {
              "schema": {
                "type": "object",
                "properties": {
                  "flag": {
                    "type": "string",
                    "enum": [
                      "a",
                      "b",
                      "c"
                    ]
                  }
                }
              }
            }
          }
        },
        "responses": {
          "201": {
            "description": "created"
          }
        }
      }
    }
  }
}