{
  "openapi": "3.0.0",
  "info": {
    "title": "synth-openapi-99a0ee6ae182",
    "version": "1.0.0"
  },
  "paths": {
    "/synth-openapi-99a0ee6ae182/items": {
      "get": {
        "responses": {
          "200": {
            "description": "ok"
          }
        }
      }
    },
    "/synth-openapi-99a0ee6ae182/auto71449": {
      "post": {
        "requestBody": {
          "content": {
            "application/json": {
              "schema": {
                "type": "object",
                "properties": {
                  "flag": {
                    "type": "string",
                    "enum": [
                      "a",
                      "b",
                      "c"
                    ]
                  }
                }
              }
            }
          }
        },
        "responses": {
          "201": {
            "description": "created"
          }
        }
      }
    },
    "/synth-openapi-99a0ee6ae182/auto44486": {
      "get": {
        "responses": {
          "200": {
            "description": "ok"
          }
        }
      }
    },
    "/synth-openapi-99a0ee6ae182/auto52324": {
      "post": {
        "requestBody": {
          "content": {
            "application/json": {
              "schema": {
                "type": "object",
                "properties": {
                  "flag": {
                    "type": "string",
                    "enum": [
                      "a",
                      "b",
                      "c"
                    ]
                  }
                }
              }
            }
          }
        },
        "responses": {
          "201": {
            "description": "created"
          }
        }
      }
    },
    "/synth-openapi-99a0ee6ae182/auto65161": {
      "post": {
        "requestBody": {
          "content": {
            "application/json": {
              "schema": {
                "type": "object",
                "properties": {
                  "flag": {
                    "type": "string",
                    "enum": [
                      "a",
                      "b",
                      "c"
                    ]
                  }
                }
              }
            }
          }
        },
        "responses": {
          "201": {
            "description": "created"
          }
        }
      }
    },
    "/synth-openapi-99a0ee6ae182/auto41637": {
      "get": {
        "responses": {
          "200": {
            "description": "ok"
          }
        }
      }
    },
    "/synth-openapi-99a0ee6ae182/auto59143": {
      "post": {
        "requestBody": {
          "content": {
            "application/json": {
              "schema": {
                "type": "object",
                "properties": {
                  "flag": {
                    "type": "string",
                    "enum": [
                      "a",
                      "b",
                      "c"
                    ]
                  }
                }
              }
            }
          }
        },
        "responses": {
          "201": {
            "description": "created"
          }
        }
      }
    },
    "/synth-openapi-99a0ee6ae182/auto91167": {
      "get": {
        "responses": {
          "200": {
            "description": "ok"
          }
        }
      }
    }
  }
}