{
  "openapi": "3.0.0",
  "info": {
    "title": "synth-openapi-cbcea5f493e2",
    "version": "1.0.0"
  },
  "paths": {
    "/synth-openapi-cbcea5f493e2/items": {
      "get": {
        "responses": {
          "200": {
            "description": "ok"
          }
        },
        "parameters": [
          {
            "name": "status",
            "in": "query",
            "schema": {
              "type": "string",
              "enum": [
                "x",
                "y",
                "z"
              ]
            },
            "required": false
          }
        ]
      }
    },
    "/synth-openapi-cbcea5f493e2/auto27549": {
      "post": {
        "requestBody": {
          "content": {
            "application/json": {
              "schema": {
                "type": "object",
                "properties": {
                  "flag": {
                    "type": "string",
                    "enum": [
                      "a",
                      "b",
                      "c"
                    ]
                  }
                }
              }
            }
          }
        },
        "responses": {
          "201": {
            "description": "created"
          }
        }
      }
    },
    "/synth-openapi-cbcea5f493e2/auto75951": {
      "post": {
        "requestBody": {
          "content": {
            "application/json": {
              "schema": {
                "type": "object",
                "properties": {
                  "flag": {
                    "type": "string",
                    "enum": [
                      "a",
                      "b",
                      "c"
                    ]
                  }
                }
              }
            }
          }
        },
        "responses": {
          "201": {
            "description": "created"
          }
        }
      }
    },
    "/synth-openapi-cbcea5f493e2/auto45451": {
      "get": {
        "responses": {
          "200": {
            "description": "ok"
          }
        }
      }
    },
    "/synth-openapi-cbcea5f493e2/auto83482": {
      "get": {
        "responses": {
          "200": {
            "description": "ok"
          }
        }
      }
    },
    "/synth-openapi-cbcea5f493e2/auto79892": {
      "get": {
        "responses": {
          "200": {
            "description": "ok"
          }
        }
      }
    },
    "/synth-openapi-cbcea5f493e2/auto70962": {
      "get": {
        "responses": {
          "200": {
            "description": "ok"
          }
        }
      }
    },
    "/synth-openapi-cbcea5f493e2/auto71920": {
      "get": {
        "responses": {
          "200": {
            "description": "ok"
          }
        }
      }
    }
  }
}