{
  "pair_id": "pair-99377c8f2019a27b79de",
  "service_name": "auth-service",
  "dataset": "openapi",
  "old_canonical": "openapi--auth-service--99377c8f--v1.canonical.json",
  "new_canonical": "openapi--auth-service--99377c8f--v2.canonical.json",
  "old": "datasets/curated/openapi/canonical/openapi--auth-service--99377c8f--v1.canonical.json",
  "new": "datasets/curated/openapi/canonical/openapi--auth-service--99377c8f--v2.canonical.json",
  "old_sha": "a49b5cda574b071043a3",
  "new_sha": "b00a4a5f77d00e6d2d2e",
  "warnings": [
    "cycle local #/components/schemas/ArrayValue",
    "cycle local #/components/schemas/ArrayValue",
    "cycle local #/components/schemas/Value",
    "cycle local #/components/schemas/Value",
    "cycle local #/components/schemas/ArrayValue",
    "cycle local #/components/schemas/ArrayValue",
    "cycle local #/components/schemas/ArrayValue",
    "cycle local #/components/schemas/ArrayValue",
    "cycle local #/components/schemas/ArrayValue",
    "cycle local #/components/schemas/Value",
    "cycle local #/components/schemas/Value",
    "cycle local #/components/schemas/ArrayValue",
    "cycle local #/components/schemas/ArrayValue",
    "cycle local #/components/schemas/ArrayValue",
    "cycle local #/components/schemas/ArrayOfArray",
    "cycle local #/components/schemas/ArrayValue",
    "cycle local #/components/schemas/ArrayValueList",
    "cycle local #/components/schemas/ArrayValueList",
    "cycle local #/components/schemas/ArrayValueList",
    "cycle local #/components/schemas/StructValue",
    "cycle local #/components/schemas/Value",
    "cycle local #/components/schemas/Value",
    "cycle local #/components/schemas/ArrayValue",
    "cycle local #/components/schemas/ArrayValue",
    "cycle local #/components/schemas/ArrayValue",
    "cycle local #/components/schemas/Value",
    "cycle local #/components/schemas/Value",
    "cycle local #/components/schemas/ArrayValue",
    "cycle local #/components/schemas/ArrayValue",
    "cycle local #/components/schemas/ArrayValue",
    "cycle local #/components/schemas/ArrayValue",
    "cycle local #/components/schemas/Value",
    "cycle local #/components/schemas/Value",
    "cycle local #/components/schemas/Value",
    "cycle local #/components/schemas/Value",
    "cycle local #/components/schemas/Value",
    "cycle local #/components/schemas/Value",
    "cycle local #/components/schemas/Value",
    "cycle local #/components/schemas/Value",
    "cycle local #/components/schemas/Value",
    "cycle local #/components/schemas/Value",
    "cycle local #/components/schemas/ArrayValueList",
    "cycle local #/components/schemas/ArrayValueList",
    "cycle local #/components/schemas/ArrayValue"
  ],
  "seed": 1840390700,
  "generated_at": "2025-11-27T18:43:07+00:00"
}