{
  "pair_id": "pair-c87a99d625828f837a2b",
  "service_name": "shipping-service",
  "dataset": "openapi",
  "old_canonical": "openapi--shipping-service--c87a99d6--v1.canonical.json",
  "new_canonical": "openapi--shipping-service--c87a99d6--v2.canonical.json",
  "old": "datasets/curated/openapi/canonical/openapi--shipping-service--c87a99d6--v1.canonical.json",
  "new": "datasets/curated/openapi/canonical/openapi--shipping-service--c87a99d6--v2.canonical.json",
  "old_sha": "099bde5d3fb88a700255",
  "new_sha": "6ba3bf6d5f5e1a4d9385",
  "warnings": [
    "cycle local #/definitions/errorResponseBody",
    "cycle local #/definitions/errorResponseBody",
    "cycle local #/definitions/errorResponseBody",
    "cycle local #/definitions/errorResponseBody",
    "cycle local #/definitions/errorResponseBody",
    "cycle local #/definitions/alertsSummaryGroupItem",
    "cycle local #/definitions/errorResponseBody",
    "cycle local #/definitions/errorResponseBody",
    "cycle local #/definitions/errorResponseBody",
    "cycle local #/definitions/errorResponseBody",
    "cycle local #/definitions/errorResponseBody",
    "cycle local #/definitions/errorResponseBody",
    "cycle local #/definitions/errorResponseBody",
    "cycle local #/definitions/errorResponseBody",
    "cycle local #/definitions/errorResponseBody",
    "cycle local #/definitions/errorResponseBody",
    "cycle local #/definitions/alertsSummaryGroupItem",
    "cycle local #/definitions/alertsSummaryGroupItem",
    "cycle local #/definitions/alertsSummaryGroupItem",
    "cycle local #/definitions/errorResponseBody",
    "cycle local #/definitions/errorResponseBody"
  ],
  "seed": 1443770465,
  "generated_at": "2025-11-27T18:45:30+00:00"
}