{
  "pair_id": "pair-596909580fe495c8fc74",
  "dataset": "openapi",
  "service_name": "catalog-service",
  "old_canonical": "openapi--catalog-service--59690958--v1.canonical.json",
  "new_canonical": "openapi--catalog-service--59690958--v2.canonical.json",
  "old": "datasets/curated_clean/openapi/canonical/openapi--catalog-service--59690958--v1.canonical.json",
  "new": "datasets/curated_clean/openapi/canonical/openapi--catalog-service--59690958--v2.canonical.json",
  "old_sha": "32c839e21fa076fbc52e",
  "new_sha": "6f2a45c9cc90a6cc9518",
  "generated_at": "2025-11-30T11:52:52+00:00",
  "producers_sample": [
    "/carts/{id}",
    "/crl/orderid",
    "/crl/userid/disable",
    "/crl/userid/enable",
    "/inventory/{id}",
    "/billing/{id}",
    "/crl/orderid/enable",
    "/crl/sku",
    "/crl/userid/disable",
    "/orders/{id}"
  ]
}